text_correction_utils-0.1.4.dist-info/METADATA
text_correction_utils-0.1.4.dist-info/WHEEL
text_correction_utils-0.1.4.dist-info/entry_points.txt
text_correction_utils-0.1.4.dist-info/license_files/LICENSE
text_correction_utils/configuration.py
text_correction_utils/version.py
text_correction_utils/tensorboard.py
text_correction_utils/__init__.py
text_correction_utils/py.typed
text_correction_utils/modules/embedding.py
text_correction_utils/modules/head.py
text_correction_utils/modules/encoder.py
text_correction_utils/modules/__init__.py
text_correction_utils/modules/grouping.py
text_correction_utils/modules/loss.py
text_correction_utils/modules/lr_scheduler.py
text_correction_utils/modules/decoder.py
text_correction_utils/modules/utils.py
text_correction_utils/modules/optimizer.py
text_correction_utils/logging.py
text_correction_utils/io.py
text_correction_utils/api/cli.py
text_correction_utils/api/__init__.py
text_correction_utils/api/corrector.py
text_correction_utils/api/utils.py
text_correction_utils/api/trainer.py
text_correction_utils/api/table.py
text_correction_utils/api/server.py
text_correction_utils/inference/__init__.py
text_correction_utils/mask.py
text_correction_utils/hook.py
text_correction_utils/cli/__init__.py
text_correction_utils/cli/dictionary.py
text_correction_utils/cli/zip_experiment.py
text_correction_utils/distributed.py
text_correction_utils/_internal.abi3.so
text_correction_utils-0.1.4.dist-info/RECORD
