Metadata-Version: 2.1
Name: text_correction_utils
Version: 0.1.4
Classifier: Programming Language :: Rust
Classifier: Programming Language :: Python :: 3
Classifier: Topic :: Scientific/Engineering :: Artificial Intelligence
Classifier: Topic :: Software Development :: Libraries
Classifier: Topic :: Text Processing
Classifier: Topic :: Utilities
Requires-Dist: torch>=1.12.0
Requires-Dist: einops>=0.6.0
Requires-Dist: numpy>=1.23.0
Requires-Dist: pyyaml>=6.0
Requires-Dist: tqdm>=4.60.0
Requires-Dist: tensorboard>=2.10.0
Requires-Dist: flask>=2.2.0
Requires-Dist: requests>=2.20.0
Requires-Dist: termcolor>=2.2.0
Requires-Dist: pytest>=6.2.0; extra == 'test'
Provides-Extra: test
License-File: LICENSE
Summary: Utilities for text correction tasks using Deep NLP
Keywords: nlp,utilities,text,correction
Author-email: Sebastian Walter <swalter@cs.uni-freiburg.de>
Requires-Python: >=3.8
Project-URL: Github, https://github.com/ad-freiburg/text-correction-utils
